ddupdate.py
ddupdate-0.0.1.data/data/share/ddupdate/dispatcher.d/50-ddupdate
ddupdate-0.0.1.data/data/share/ddupdate/plugins/changeip.py
ddupdate-0.0.1.data/data/share/ddupdate/plugins/default_if.py
ddupdate-0.0.1.data/data/share/ddupdate/plugins/default_web.py
ddupdate-0.0.1.data/data/share/ddupdate/plugins/dnsexit.py
ddupdate-0.0.1.data/data/share/ddupdate/plugins/dry_run.py
ddupdate-0.0.1.data/data/share/ddupdate/plugins/dtdns.py
ddupdate-0.0.1.data/data/share/ddupdate/plugins/duckdns.py
ddupdate-0.0.1.data/data/share/ddupdate/plugins/dynu.py
ddupdate-0.0.1.data/data/share/ddupdate/plugins/freedns.py
ddupdate-0.0.1.data/data/share/ddupdate/plugins/hardcoded_if.py
ddupdate-0.0.1.data/data/share/ddupdate/plugins/ip_disabled.py
ddupdate-0.0.1.data/data/share/ddupdate/plugins/ip_from_cmd.py
ddupdate-0.0.1.data/data/share/ddupdate/plugins/no_ip.py
ddupdate-0.0.1.data/data/share/ddupdate/plugins/plugins_base.py
ddupdate-0.0.1.data/data/share/doc/ddupdate/LICENSE.txt
ddupdate-0.0.1.data/data/share/doc/ddupdate/README.md
ddupdate-0.0.1.data/data/share/doc/ddupdate/ddupdate.8.html
ddupdate-0.0.1.data/data/share/man/man8/ddupdate.8
ddupdate-0.0.1.data/scripts/ddupdate
ddupdate-0.0.1.dist-info/DESCRIPTION.rst
ddupdate-0.0.1.dist-info/METADATA
ddupdate-0.0.1.dist-info/RECORD
ddupdate-0.0.1.dist-info/WHEEL
ddupdate-0.0.1.dist-info/metadata.json
ddupdate-0.0.1.dist-info/top_level.txt
etc/ddupdate.conf
lib/systemd/system/ddupdate.service
lib/systemd/system/ddupdate.timer
