Metadata-Version: 2.0
Name: ddupdate
Version: 0.0.1
Summary: Update dns data for dynamic ip addresses
Home-page: http://github.com/leamas/ddupdate
Author: Alec Leamas
Author-email: alec.leamas@nowhere.net
License: MIT
Keywords: dyndns,dhcp,dns
Platform: UNKNOWN
Classifier: Development Status :: 3 - Alpha
Classifier: Intended Audience :: End Users/Desktop
Classifier: Topic :: Software Development :: Build Tools
Classifier: Topic :: System :: Networking
Classifier: License :: OSI Approved :: MIT License
Classifier: Programming Language :: Python :: 3.4
Requires-Dist: straight.plugin
